{
    "name": "#zm_zodt8_packapunch",
    "delayBetweenRepSoundsDuration": 0,
    "earthquakeOnRepair": 0,
    "earthquakeMinScale": 0.3,
    "earthquakeMaxScale": 0.4,
    "earthquakeMinDuration": 0.2,
    "earthquakeMaxDuration": 0.4,
    "earthquakeRadius": 150,
    "numBoardsInBarrier": 6,
    "autoHideOpenPieces": 0,
    "taunts": 0,
    "reachThroughAttacks": 0,
    "numAttackSlots": 1,
    "attackSpotHorzOffset": 0,
    "boards": [
        {
            "boardModel": "#hash_639617ad8b487dc3",
            "boardAnim": "#p8_fxanim_zm_pap_pedestal_static_anim",
            "staticAnim": "#p8_fxanim_zm_pap_pedestal_static_anim",
            "repairEffect1Offset": "0 0 0",
            "repairEffect2Offset": "0 0 0",
            "minPause": 0.3,
            "maxPause": 0.6,
            "numRepsToPullProBoard": 3
        },
        {
            "boardModel": "#hash_129339f4a4da8ea2",
            "tearAnim": "#p8_fxanim_zm_base_packapunch_working_take_gun_anim",
            "boardAnim": "#o_zombie_base_packapunch_working_eject_gun",
            "pauseAndRepeatRepSound": "#hash_1",
            "repairEffect1Offset": "0 0 0",
            "repairEffect2Offset": "0 0 0",
            "minPause": 0.3,
            "maxPause": 0.6,
            "numRepsToPullProBoard": 3
        },
        {
            "boardModel": "#p7_zm_der2_vending_packapunch_sign_wait",
            "tearAnim": "#o_zombie_base_packapunch_flag_up",
            "boardAnim": "#o_zombie_base_packapunch_flag_down",
            "pauseAndRepeatRepSound": "#hash_1",
            "repairEffect1Offset": "0 0 0",
            "repairEffect2Offset": "0 0 0",
            "minPause": 0.3,
            "maxPause": 0.6,
            "numRepsToPullProBoard": 3
        },
        {
            "boardModel": "#p7_zm_vending_packapunch_weapon",
            "tearAnim": "#p8_fxanim_zm_packapunch_worldguns_taken",
            "boardAnim": "#p8_fxanim_zm_packapunch_worldguns_ejected",
            "pauseAndRepeatRepSound": "#hash_1",
            "repairEffect1Offset": "0 0 0",
            "repairEffect2Offset": "0 0 0",
            "minPause": 1,
            "maxPause": 1,
            "numRepsToPullProBoard": 3
        },
        {
            "boardModel": "#hash_129339f4a4da8ea2",
            "tearAnim": "#p8_fxanim_zm_pap_disassemble_anim",
            "boardAnim": "#hash_6eeafc7dbcbcde96",
            "staticAnim": "#hash_586b870b2b35eb14",
            "pauseAndRepeatRepSound": "#hash_1",
            "repairEffect1Offset": "0 0 0",
            "repairEffect2Offset": "0 0 0",
            "minPause": 0.3,
            "maxPause": 0.6,
            "numRepsToPullProBoard": 3
        },
        {
            "boardModel": "#p7_zm_vending_packapunch_weapon",
            "tearAnim": "#p8_fxanim_zm_packapunch_worldguns_small_taken",
            "boardAnim": "#p8_fxanim_zm_packapunch_worldguns_small_ejected",
            "repairEffect1Offset": "0 0 0",
            "repairEffect2Offset": "0 0 0",
            "minPause": 0.3,
            "maxPause": 0.6,
            "numRepsToPullProBoard": 3
        }
    ]
}