{
    "name": "#maps/mp/mp_jungle2_alt.d3dbsp",
    "isInUse": true,
    "primaryLights": 106,
    "lightExploders": [
        {
            "lightExploderName": "#hash_7e17d35a668424",
            "triggerData": [
                {
                    "delayOn": 0,
                    "delayOff": 0,
                    "fadeIn": 0,
                    "fadeOut": 0,
                    "primaryLightIndex": 92,
                    "reversed": false
                },
                {
                    "delayOn": 0,
                    "delayOff": 0,
                    "fadeIn": 0,
                    "fadeOut": 0,
                    "primaryLightIndex": 93,
                    "reversed": false
                },
                {
                    "delayOn": 0,
                    "delayOff": 0,
                    "fadeIn": 0,
                    "fadeOut": 0,
                    "primaryLightIndex": 94,
                    "reversed": false
                },
                {
                    "delayOn": 0,
                    "delayOff": 0,
                    "fadeIn": 0,
                    "fadeOut": 0,
                    "primaryLightIndex": 95,
                    "reversed": false
                },
                {
                    "delayOn": 0,
                    "delayOff": 0,
                    "fadeIn": 0,
                    "fadeOut": 0,
                    "primaryLightIndex": 96,
                    "reversed": false
                },
                {
                    "delayOn": 0,
                    "delayOff": 0,
                    "fadeIn": 0,
                    "fadeOut": 0,
                    "primaryLightIndex": 97,
                    "reversed": false
                },
                {
                    "delayOn": 0,
                    "delayOff": 0,
                    "fadeIn": 0,
                    "fadeOut": 0,
                    "primaryLightIndex": 98,
                    "reversed": false
                },
                {
                    "delayOn": 0,
                    "delayOff": 0,
                    "fadeIn": 0,
                    "fadeOut": 0,
                    "primaryLightIndex": 99,
                    "reversed": false
                },
                {
                    "delayOn": 0,
                    "delayOff": 0,
                    "fadeIn": 0,
                    "fadeOut": 0,
                    "primaryLightIndex": 100,
                    "reversed": false
                },
                {
                    "delayOn": 0,
                    "delayOff": 0,
                    "fadeIn": 0,
                    "fadeOut": 0,
                    "primaryLightIndex": 101,
                    "reversed": false
                },
                {
                    "delayOn": 0,
                    "delayOff": 0,
                    "fadeIn": 0,
                    "fadeOut": 0,
                    "primaryLightIndex": 102,
                    "reversed": false
                },
                {
                    "delayOn": 0,
                    "delayOff": 0,
                    "fadeIn": 0,
                    "fadeOut": 0,
                    "primaryLightIndex": 103,
                    "reversed": false
                },
                {
                    "delayOn": 0,
                    "delayOff": 0,
                    "fadeIn": 0,
                    "fadeOut": 0,
                    "primaryLightIndex": 104,
                    "reversed": false
                },
                {
                    "delayOn": 0,
                    "delayOff": 0,
                    "fadeIn": 0,
                    "fadeOut": 0,
                    "primaryLightIndex": 105,
                    "reversed": false
                }
            ]
        }
    ],
    "probeExploders": [
        {
            "lightExploderName": "#hash_7e17d35a668424",
            "triggerData": [
                {
                    "probeID": 149,
                    "volumeID": 0,
                    "delayOn": 0,
                    "delayOff": 0,
                    "fadeIn": 0,
                    "fadeOut": 0,
                    "reversed": false
                },
                {
                    "probeID": 150,
                    "volumeID": 0,
                    "delayOn": 0,
                    "delayOff": 0,
                    "fadeIn": 0,
                    "fadeOut": 0,
                    "reversed": false
                }
            ]
        }
    ],
    "sunVolumeProbeCount": [
        150,
        1
    ],
    "probeGuids": [
        3906517724,
        2853306492,
        2853306105,
        3802629221,
        2853306489,
        49598474,
        2853306153,
        2853306495,
        2446699693,
        745650476,
        2853306450,
        285673286,
        3152305453,
        2853306156,
        2853306246,
        2853306912,
        2792880740,
        2853306465,
        2792880737,
        392029961,
        2853306504,
        2853306453,
        2853306243,
        2853306252,
        2853306255,
        2853306438,
        2853306669,
        2853306444,
        2853306561,
        2853306459,
        2853306207,
        2853306534,
        2853306189,
        2853306432,
        2853306426,
        2853306927,
        2853306261,
        2853306429,
        2853306414,
        2853306132,
        2853306417,
        2853306420,
        2853306627,
        2853306063,
        2853306099,
        2853306720,
        2853306567,
        2853306714,
        2853306300,
        2853306069,
        2853306471,
        2853306477,
        3422199672,
        2853306456,
        2397515435,
        2079505792,
        2853306183,
        3717825150,
        2837569699,
        1188301908,
        2853306558,
        2853306501,
        2853306474,
        2853306519,
        2853306198,
        2853306081,
        2853306144,
        2853306138,
        2853306141,
        2853306636,
        619616727,
        2853306837,
        2853306240,
        2853306381,
        2853306219,
        2853306210,
        2853306840,
        2853306147,
        2853306216,
        2853306150,
        2853306213,
        2853306135,
        2853306384,
        2853306396,
        2853306201,
        2853306546,
        2853306528,
        2853306186,
        1736873818,
        2025011344,
        2853306096,
        2853306531,
        2853306372,
        2853306090,
        2853306549,
        2853306102,
        2853306606,
        2853306507,
        2853306480,
        2853306171,
        2853306363,
        2853306624,
        2853306540,
        2959693677,
        2853306333,
        2853306342,
        448130368,
        2853306060,
        2853306345,
        3451921749,
        2853306126,
        2853306120,
        2853306123,
        2853306117,
        1673566727,
        2853306114,
        2363064062,
        2853306075,
        1430072216,
        2853306093,
        2853306303,
        2853306354,
        287385515,
        1584367393,
        2853306066,
        2853306084,
        2853306408,
        2853306087,
        1912253667,
        2853306405,
        2853306378,
        2853306072,
        2853306315,
        2853306285,
        2151104796,
        2853306339,
        2853306294,
        2853306330,
        2853306270,
        1090180131,
        3985458555,
        2853306327,
        2253219358,
        2853306336,
        448130365,
        2517562331,
        2853306078,
        2853306510,
        3716372367,
        3716372361,
        0
    ]
}