{
    "configstringfiletype": "scriptbundle",
    "value2": "1",
    "value3": "2",
    "value1": "0",
    "value4": "3",
    "type": "gamesettings",
    "hash_5a6dee5a": 0,
    "name": "gun_selection",
    "displayname": "localized17#menu/gunlist",
    "label4": "localized17#menu/gunlist_random",
    "label1": "localized17#menu/gunlist_normal",
    "label3": "localized17#menu/gunlist_marksman",
    "label2": "localized17#menu/gunlist_cqb",
    "hash_54e336e4": 0,
    "optionscount": 4,
    "hinttext4": "localized17#menu/gunlist_random_hint",
    "hinttext3": "localized17#menu/gunlist_marksman_hint",
    "hinttext2": "localized17#menu/gunlist_cqb_hint",
    "hinttext1": "localized17#menu/gunlist_normal_hint",
    "hash_765cfd09": 0,
    "setting": "gunSelection",
    "isenableddisabled": 0
}