{
    "contentsdetaileddescincludelist": [
        {
            "hash_74949c76508e944f:hash_826726a": "localized17#hash_74949c76508e944f"
        },
        {
            "heroes/firebreak:hash_826726a": "localized17#heroes/firebreak"
        }
    ],
    "contracticon": "image#hash_643448de997d0d2e",
    "hash_d0100eab": 2,
    "relateditemname": "localized17#heroes/firebreak",
    "contracttitle": "localized17#hash_74949c76508e944f",
    "name": "loot_contract_firebreak_muertos",
    "contractdescription": "localized17#hash_25105a1e4c1d1e63",
    "white": "#white",
    "hash_69164c20fbcba78d:hash_1c057e8c": "image#hash_69164c20fbcba78d",
    "hash_1228188324cf56e:hash_e08fc162": "localized17#hash_1228188324cf56e"
}